Metadata-Version: 2.4
Name: sylvain-tts
Version: 0.0.1
Summary: Deep learning for Text to Speech.
Project-URL: Homepage, https://github.com/idiap/coqui-ai-TTS
Project-URL: Documentation, https://coqui-tts.readthedocs.io
Project-URL: Repository, https://github.com/idiap/coqui-ai-TTS
Project-URL: Issues, https://github.com/idiap/coqui-ai-TTS/issues
Project-URL: Discussions, https://github.com/idiap/coqui-ai-TTS/discussions
Author-email: Eren Gölge <egolge@coqui.ai>, Enno Hermann <enno.hermann@gmail.com>
Maintainer-email: Sylvain Chan <me@sylvain.hk>
License: MPL-2.0
License-File: LICENSE.txt
Classifier: Development Status :: 3 - Alpha
Classifier: Intended Audience :: Developers
Classifier: Intended Audience :: Science/Research
Classifier: License :: OSI Approved :: Mozilla Public License 2.0 (MPL 2.0)
Classifier: Operating System :: POSIX :: Linux
Classifier: Programming Language :: Python
Classifier: Programming Language :: Python :: 3
Classifier: Programming Language :: Python :: 3.10
Classifier: Programming Language :: Python :: 3.11
Classifier: Programming Language :: Python :: 3.12
Classifier: Topic :: Multimedia
Classifier: Topic :: Multimedia :: Sound/Audio
Classifier: Topic :: Multimedia :: Sound/Audio :: Speech
Classifier: Topic :: Scientific/Engineering :: Artificial Intelligence
Classifier: Topic :: Software Development
Classifier: Topic :: Software Development :: Libraries :: Python Modules
Requires-Python: <3.13,>=3.10
Requires-Dist: anyascii>=0.3.0
Requires-Dist: coqpit-config<0.3.0,>=0.2.0
Requires-Dist: cython>=3.0.0
Requires-Dist: einops>=0.6.0
Requires-Dist: encodec>=0.1.1
Requires-Dist: fsspec[http]>=2023.6.0
Requires-Dist: gruut[de,es,fr]>=2.4.0
Requires-Dist: inflect>=5.6.0
Requires-Dist: librosa>=0.11.0
Requires-Dist: matplotlib>=3.8.4
Requires-Dist: monotonic-alignment-search>=0.1.0
Requires-Dist: num2words>=0.5.14
Requires-Dist: numpy>=1.26.0
Requires-Dist: packaging>=23.1
Requires-Dist: pysbd>=0.3.4
Requires-Dist: pyyaml>=6.0
Requires-Dist: scipy>=1.13.0
Requires-Dist: soundfile>=0.12.0
Requires-Dist: sylvain-tts-trainer<0.4.0,>=0.3.0
Requires-Dist: torch>=2.1
Requires-Dist: torchaudio>=2.1.0
Requires-Dist: tqdm>=4.64.1
Requires-Dist: transformers>=4.52.1
Requires-Dist: typing-extensions>=4.10
Provides-Extra: all
Requires-Dist: bangla>=0.0.2; extra == 'all'
Requires-Dist: bnnumerizer>=0.0.2; extra == 'all'
Requires-Dist: bnunicodenormalizer>=0.1.0; extra == 'all'
Requires-Dist: bokeh>=3.0.3; extra == 'all'
Requires-Dist: cutlet>=0.2.0; extra == 'all'
Requires-Dist: flask>=3.0.0; extra == 'all'
Requires-Dist: fugashi[unidic-lite]>=1.3.0; extra == 'all'
Requires-Dist: g2pkk>=0.1.1; extra == 'all'
Requires-Dist: hangul-romanize>=0.1.0; extra == 'all'
Requires-Dist: jamo>=0.4.1; extra == 'all'
Requires-Dist: jieba>=0.42.1; extra == 'all'
Requires-Dist: pandas<3.0,>=1.4; extra == 'all'
Requires-Dist: pip>=22.2; extra == 'all'
Requires-Dist: pypinyin>=0.40.0; extra == 'all'
Requires-Dist: umap-learn>=0.5.1; extra == 'all'
Provides-Extra: bn
Requires-Dist: bangla>=0.0.2; extra == 'bn'
Requires-Dist: bnnumerizer>=0.0.2; extra == 'bn'
Requires-Dist: bnunicodenormalizer>=0.1.0; extra == 'bn'
Provides-Extra: ja
Requires-Dist: cutlet>=0.2.0; extra == 'ja'
Requires-Dist: fugashi[unidic-lite]>=1.3.0; extra == 'ja'
Provides-Extra: ko
Requires-Dist: g2pkk>=0.1.1; extra == 'ko'
Requires-Dist: hangul-romanize>=0.1.0; extra == 'ko'
Requires-Dist: jamo>=0.4.1; extra == 'ko'
Requires-Dist: pip>=22.2; extra == 'ko'
Provides-Extra: languages
Requires-Dist: bangla>=0.0.2; extra == 'languages'
Requires-Dist: bnnumerizer>=0.0.2; extra == 'languages'
Requires-Dist: bnunicodenormalizer>=0.1.0; extra == 'languages'
Requires-Dist: cutlet>=0.2.0; extra == 'languages'
Requires-Dist: fugashi[unidic-lite]>=1.3.0; extra == 'languages'
Requires-Dist: g2pkk>=0.1.1; extra == 'languages'
Requires-Dist: hangul-romanize>=0.1.0; extra == 'languages'
Requires-Dist: jamo>=0.4.1; extra == 'languages'
Requires-Dist: jieba>=0.42.1; extra == 'languages'
Requires-Dist: pip>=22.2; extra == 'languages'
Requires-Dist: pypinyin>=0.40.0; extra == 'languages'
Provides-Extra: notebooks
Requires-Dist: bokeh>=3.0.3; extra == 'notebooks'
Requires-Dist: pandas<3.0,>=1.4; extra == 'notebooks'
Requires-Dist: umap-learn>=0.5.1; extra == 'notebooks'
Provides-Extra: server
Requires-Dist: flask>=3.0.0; extra == 'server'
Provides-Extra: zh
Requires-Dist: jieba>=0.42.1; extra == 'zh'
Requires-Dist: pypinyin>=0.40.0; extra == 'zh'
